<?xml version="1.0" encoding="UTF-8" standalone="no"?>
<databaseChangeLog xmlns="http://www.liquibase.org/xml/ns/dbchangelog" xmlns:ext="http://www.liquibase.org/xml/ns/dbchangelog-ext" xmlns:xsi="http://www.w3.org/2001/XMLSchema-instance" xsi:schemaLocation="http://www.liquibase.org/xml/ns/dbchangelog http://www.liquibase.org/xml/ns/dbchangelog/dbchangelog-3.3.xsd http://www.liquibase.org/xml/ns/dbchangelog-ext http://www.liquibase.org/xml/ns/dbchangelog/dbchangelog-ext.xsd">
    <changeSet author="Hidem (generated)" id="1424540000229-1">
        <dropColumn columnName="id_level" tableName="t_levels"/>
    </changeSet>
    <changeSet author="Hidem (generated)" id="1424540000229-2">
        <dropColumn columnName="id_picture" tableName="t_pictures"/>
    </changeSet>
    <changeSet author="Hidem (generated)" id="1424540000229-3">
        <dropColumn columnName="id_species" tableName="t_species"/>
    </changeSet>
    <changeSet author="Hidem (generated)" id="1424540000229-4">
        <dropColumn columnName="id_tag" tableName="t_tags"/>
    </changeSet>
    <changeSet author="Hidem (generated)" id="1424540000229-5">
        <dropColumn columnName="level_played" tableName="t_userstars"/>
    </changeSet>
</databaseChangeLog>
